calculator2004/__init__.py
calculator2004/arithmetic.py
calculator2004-0.1.0.dist-info/METADATA
calculator2004-0.1.0.dist-info/WHEEL
calculator2004-0.1.0.dist-info/top_level.txt
calculator2004-0.1.0.dist-info/RECORD
