Metadata-Version: 2.2
Name: calculator2004
Version: 0.1.0
Summary: A simple calculator package
Home-page: https://github.com/jpsz2004/calculator
Author: Juan Pablo Sánchez Zapata
Author-email: juan.sanchez8@utp.edu.co
Classifier: Programming Language :: Python :: 3
Classifier: License :: OSI Approved :: MIT License
Classifier: Operating System :: OS Independent
Requires-Python: >=3.6
Dynamic: author
Dynamic: author-email
Dynamic: classifier
Dynamic: description
Dynamic: description-content-type
Dynamic: home-page
Dynamic: requires-python
Dynamic: summary
